[
  {
    "origin": "LAX",
    "destination": "SFO"
  },
  {
    "origin": "LAX",
    "destination": "JFK"
  },
  {
    "origin": "ATL",
    "destination": "BOS"
  },
  {
    "origin": "SEA",
    "destination": "MIA"
  },
  {
    "origin": "SEA",
    "destination": "MIA",
    "maxFlights": 2
  },
  {
    "origin": "SEA",
    "destination": "MIA",
    "maxFlights": 0
  },
  {
    "origin": "LAX",
    "destination": "ORD"
  },
  {
    "origin": "DEN",
    "destination": "JFK",
    "maxFlights": 3
  },
  {
    "origin": "MIA",
    "destination": "SEA",
    "maxFlights": 4
  },
  {
    "origin": "LAX",
    "destination": "LAX",
    "maxFlights": 0
  }
]